<?xml version="1.0" encoding="UTF-8"?>
<work xmlns="http://www.tei-c.org/ns/1.0" xml:id="work_4" status="checked">
  <label xml:id="label-9289cc2d-5a99-4d2e-823b-6d150983e0d9" labelImportance="primary" labelGiver="science" labelType="name" lang="de">Alexius</label>
<idno type="gnd">http://d-nb.info/gnd/4576130-9</idno>
    
    
    
    
    
<description/>
    <comment/>
    <ref type="event" target="event_8638fb15-2d3e-40e5-800a-d5c650efbfce"/>
    <ref type="event" target="event_49c2bbea-2bcf-45b6-8a58-ce49d635a048"/>
    <ref type="event" target="event_cf0eda52-d157-4028-ac20-3b681ab63326"/>
    <idno type="census">http://www.handschriftencensus.de/werke/663</idno>
    <ref type="author" target="person_1" cert="certain"/>
</work>